chartartappbuilder/__init__.py
chartartappbuilder/app_builder.py
chartartappbuilder/conftest.py
chartartappbuilder/helpers.py
chartartappbuilder/plot.py
chartartappbuilder/simple_eda_template.py
chartartappbuilder/test_plot.py
chartartappbuilder/tests/__init__.py
chartartappbuilder/tests/test_simple.py
chartart_appbuilder-0.0.1.dev3.dist-info/LICENSE
chartart_appbuilder-0.0.1.dev3.dist-info/METADATA
chartart_appbuilder-0.0.1.dev3.dist-info/WHEEL
chartart_appbuilder-0.0.1.dev3.dist-info/top_level.txt
chartart_appbuilder-0.0.1.dev3.dist-info/RECORD
