Metadata-Version: 2.1
Name: chartart-appbuilder
Version: 0.0.1.dev3
Summary: ChartArt AppBuilder python package
Home-page: https://github.com/pypa/sampleproject
Author: BR-Advisers
Author-email: info@br-advisers.com
Project-URL: Bug Tracker, https://github.com/pypa/sampleproject/issues
Keywords: chartart,NLP
Classifier: Programming Language :: Python :: 3
Classifier: License :: OSI Approved :: MIT License
Classifier: Operating System :: OS Independent
Requires-Python: >=3.6
License-File: LICENSE
Requires-Dist: pandas
Requires-Dist: numpy
Requires-Dist: ipython
Requires-Dist: ipykernel
Requires-Dist: ipynbname
Requires-Dist: openai
Requires-Dist: together
Requires-Dist: api-client
